README.md
setup.py
mdcount/__init__.py
mdcount/countFile.py
mdcount/stringOp.py
mdcount.egg-info/PKG-INFO
mdcount.egg-info/SOURCES.txt
mdcount.egg-info/dependency_links.txt
mdcount.egg-info/requires.txt
mdcount.egg-info/top_level.txt